AutoPostTelegram/__init__.py
AutoPostTelegram-1.0.3.dist-info/LICENSE
AutoPostTelegram-1.0.3.dist-info/METADATA
AutoPostTelegram-1.0.3.dist-info/WHEEL
AutoPostTelegram-1.0.3.dist-info/top_level.txt
AutoPostTelegram-1.0.3.dist-info/RECORD
