Metadata-Version: 2.1
Name: AutoPostTelegram
Version: 1.0.3
Summary: An Telegram Auto Post Package
Home-page: https://github.com/AasfCyberKing/AutoPostTelegram/
Author: Aasfcyberking
Author-email: aasfvl@gmail.com
License: License :: OSI Approved :: GNU Lesser General Public License v3 (LGPLv3)
Requires-Python: >=3.6
License-File: LICENSE
Requires-Dist: requests
Requires-Dist: datetime
